primerl/__init__.py
primerl/core.py
piql-0.0.0.dev1.dist-info/METADATA
piql-0.0.0.dev1.dist-info/WHEEL
piql-0.0.0.dev1.dist-info/top_level.txt
piql-0.0.0.dev1.dist-info/RECORD
