Metadata-Version: 2.4
Name: piql
Version: 0.0.0.dev1
Summary: Best quant library in the solar system
Author-email: Jackmin Ong <jackmin@primeintellect.ai>
License: MIT
Project-URL: Homepage, https://github.com/PrimeIntellect-ai
Project-URL: Bug Tracker, https://github.com/PrimeIntellect-ai
Classifier: Programming Language :: Python :: 3
Classifier: License :: OSI Approved :: MIT License
Classifier: Operating System :: OS Independent
Requires-Python: >=3.7
